spotify_interlude/__init__.py
spotify_interlude/audio_session.py
spotify_interlude/cli.py
spotify_interlude/core.py
spotify_interlude/spotify.py
spotify_interlude-0.1.2.dist-info/entry_points.txt
spotify_interlude-0.1.2.dist-info/LICENSE
spotify_interlude-0.1.2.dist-info/WHEEL
spotify_interlude-0.1.2.dist-info/METADATA
spotify_interlude-0.1.2.dist-info/RECORD
